[
  {
    "name": "HUM",
    "statistics": [
      {
        "type": "health",
        "label": "points de vie",
        "value": 150,
        "progress_index": 2
      },
      {
        "type": "mana",
        "label": "points de mana",
        "value": 30,
        "progress_index": 2
      },
      {
        "type": "health_regen",
        "label": "régénération",
        "value": 5,
        "progress_index": 1
      },
      {
        "type": "mana_regen",
        "label": "récupération",
        "value": 2,
        "progress_index": 1
      },
      {
        "type": "attack_damages",
        "label": "dégâts physiques",
        "value": 15,
        "progress_index": 5
      },
      {
        "type": "dark_power",
        "label": "magie noire",
        "value": 5,
        "progress_index": 2
      },
      {
        "type": "light_power",
        "label": "magie blanche",
        "value": 5,
        "progress_index": 2
      },
      {
        "type": "armor",
        "label": "armure",
        "value": 5,
        "progress_index": 2
      },
      {
        "type": "protection",
        "label": "protection",
        "value": 5,
        "progress_index": 2
      },
      {
        "type": "blessing",
        "label": "bénédiction",
        "value": 5,
        "progress_index": 2
      },
      {
        "type": "swiftness",
        "label": "vitesse",
        "value": 5,
        "progress_index": 2
      },
      {
        "type": "dodge",
        "label": "esquive",
        "value": 5,
        "progress_index": 2
      }
    ],
    "availableRoles": ["WARR", "MAGE", "PRST"]
  },
  {
    "name": "ELF",
    "statistics": [
      {
        "type": "health",
        "label": "points de vie",
        "value": 150,
        "progress_index": 2
      },
      {
        "type": "mana",
        "label": "points de mana",
        "value": 30,
        "progress_index": 2
      },
      {
        "type": "health_regen",
        "label": "régénération",
        "value": 5,
        "progress_index": 1
      },
      {
        "type": "mana_regen",
        "label": "récupération",
        "value": 2,
        "progress_index": 1
      },
      {
        "type": "attack_damages",
        "label": "dégâts physiques",
        "value": 15,
        "progress_index": 5
      },
      {
        "type": "dark_power",
        "label": "magie noire",
        "value": 5,
        "progress_index": 2
      },
      {
        "type": "light_power",
        "label": "magie blanche",
        "value": 5,
        "progress_index": 2
      },
      {
        "type": "armor",
        "label": "armure",
        "value": 5,
        "progress_index": 2
      },
      {
        "type": "protection",
        "label": "protection",
        "value": 5,
        "progress_index": 2
      },
      {
        "type": "blessing",
        "label": "bénédiction",
        "value": 5,
        "progress_index": 2
      },
      {
        "type": "swiftness",
        "label": "vitesse",
        "value": 5,
        "progress_index": 2
      },
      {
        "type": "dodge",
        "label": "esquive",
        "value": 5,
        "progress_index": 2
      }
    ],
    "availableRoles": ["MAGE", "PRST"]
  },
  {
    "name": "DWA",
    "statistics": [
      {
        "type": "health",
        "label": "points de vie",
        "value": 150,
        "progress_index": 2
      },
      {
        "type": "mana",
        "label": "points de mana",
        "value": 30,
        "progress_index": 2
      },
      {
        "type": "health_regen",
        "label": "régénération",
        "value": 5,
        "progress_index": 1
      },
      {
        "type": "mana_regen",
        "label": "récupération",
        "value": 2,
        "progress_index": 1
      },
      {
        "type": "attack_damages",
        "label": "dégâts physiques",
        "value": 15,
        "progress_index": 5
      },
      {
        "type": "dark_power",
        "label": "magie noire",
        "value": 5,
        "progress_index": 2
      },
      {
        "type": "light_power",
        "label": "magie blanche",
        "value": 5,
        "progress_index": 2
      },
      {
        "type": "armor",
        "label": "armure",
        "value": 5,
        "progress_index": 2
      },
      {
        "type": "protection",
        "label": "protection",
        "value": 5,
        "progress_index": 2
      },
      {
        "type": "blessing",
        "label": "bénédiction",
        "value": 5,
        "progress_index": 2
      },
      {
        "type": "swiftness",
        "label": "vitesse",
        "value": 5,
        "progress_index": 2
      },
      {
        "type": "dodge",
        "label": "esquive",
        "value": 5,
        "progress_index": 2
      }
    ],
    "availableRoles": ["WARR", "PRST"]
  }
]
